clients/__init__.py
clients/http.py
tests/__init__.py
tests/unit/__init__.py
tests/unit/test_async_request.py
tests/unit/test_mock.py
tests/unit/test_request.py
python_clients-1.2.1.dist-info/METADATA
python_clients-1.2.1.dist-info/WHEEL
python_clients-1.2.1.dist-info/top_level.txt
python_clients-1.2.1.dist-info/RECORD
