Metadata-Version: 2.1
Name: python-clients
Version: 1.2.1
Summary: This library implements wrapper for different python interfaces
Home-page: https://github.com/Hedgehogues/python-clients
Author: Egor Urvanov
Author-email: hedgehogues@bk.ru
License: UNKNOWN
Platform: UNKNOWN
Classifier: Programming Language :: Python :: 3.7
Classifier: Operating System :: OS Independent
Requires-Dist: requests (>=2.24.0)
Requires-Dist: aiohttp (>=3.6.2)
Requires-Dist: cachecontrol (>=0.12.5)
